<?xml encoding="UTF-8" version="1.0"?>
<actions><action><icon>accessories-text-editor</icon><name>Sublime Text</name><command>s %F</command><description>Open the file in Sublime</description><patterns>*</patterns><audio-files/><image-files/><other-files/><text-files/><video-files/></action><action><icon>Terminal</icon><name>Open Terminal Here</name><command>exo-open --working-directory %f --launch TerminalEmulator</command><description>Example for a custom action</description><patterns>*</patterns><directories/></action><action><icon></icon><name>Search...</name><command>gnome-search-tool --path=%f</command><description>Search using Gnome-search-tool</description><patterns>*</patterns><directories/></action><action><icon></icon><name>Open a root Thunar here</name><command>gksu thunar %f</command><description>Open a root Thunar here</description><patterns>*</patterns><directories/></action><action><icon>meld</icon><name>Compare</name><command>meld %F</command><description></description><patterns>*</patterns><directories/><audio-files/><image-files/><other-files/><text-files/><video-files/></action></actions>
